jbt/__init__.py
jbt/_modidx.py
jbt/core.py
jbt/imports.py
jbt-0.0.5.dist-info/LICENSE
jbt-0.0.5.dist-info/METADATA
jbt-0.0.5.dist-info/WHEEL
jbt-0.0.5.dist-info/entry_points.txt
jbt-0.0.5.dist-info/top_level.txt
jbt-0.0.5.dist-info/RECORD
