Metadata-Version: 2.1
Name: jbt
Version: 0.0.5
Summary: Vision library for JBT.
Home-page: https://github.com/HamzaFarhan/jbt
Author: HamzaFarhan
Author-email: thehamza96@gmail.com
License: Apache Software License 2.0
Keywords: nbdev jupyter notebook python
Classifier: Development Status :: 4 - Beta
Classifier: Intended Audience :: Developers
Classifier: Natural Language :: English
Classifier: Programming Language :: Python :: 3.7
Classifier: Programming Language :: Python :: 3.8
Classifier: Programming Language :: Python :: 3.9
Classifier: Programming Language :: Python :: 3.10
Classifier: License :: OSI Approved :: Apache Software License
Requires-Python: >=3.7
License-File: LICENSE
Requires-Dist: absl-py
Requires-Dist: astunparse
Requires-Dist: boto3
Requires-Dist: botocore
Requires-Dist: cachetools
Requires-Dist: charset-normalizer
Requires-Dist: click
Requires-Dist: contourpy
Requires-Dist: cryptography
Requires-Dist: cycler
Requires-Dist: decorator
Requires-Dist: docutils
Requires-Dist: dreamai
Requires-Dist: execnb
Requires-Dist: fastcore
Requires-Dist: filelock
Requires-Dist: fire
Requires-Dist: fonttools
Requires-Dist: ghapi
Requires-Dist: gitdb
Requires-Dist: gitpython
Requires-Dist: google-auth
Requires-Dist: google-auth-oauthlib
Requires-Dist: grpcio
Requires-Dist: huggingface-hub
Requires-Dist: imageio
Requires-Dist: imageio-ffmpeg
Requires-Dist: importlib-metadata
Requires-Dist: imutils
Requires-Dist: jaraco-classes
Requires-Dist: jbt
Requires-Dist: jeepney
Requires-Dist: jmespath
Requires-Dist: keyring
Requires-Dist: kiwisolver
Requires-Dist: markdown
Requires-Dist: markdown-it-py
Requires-Dist: matplotlib
Requires-Dist: mdurl
Requires-Dist: more-itertools
Requires-Dist: moviepy
Requires-Dist: nbdev
Requires-Dist: numpy
Requires-Dist: oauthlib
Requires-Dist: opencv-python
Requires-Dist: pandas
Requires-Dist: pillow
Requires-Dist: pkginfo
Requires-Dist: proglog
Requires-Dist: protobuf
Requires-Dist: pyasn1
Requires-Dist: pyasn1-modules
Requires-Dist: pybboxes
Requires-Dist: pygments
Requires-Dist: pyparsing
Requires-Dist: pytz
Requires-Dist: pyyaml
Requires-Dist: readme-renderer
Requires-Dist: requests
Requires-Dist: requests-oauthlib
Requires-Dist: requests-toolbelt
Requires-Dist: rfc3986
Requires-Dist: rich
Requires-Dist: rsa
Requires-Dist: s3transfer
Requires-Dist: sahi
Requires-Dist: scipy
Requires-Dist: seaborn
Requires-Dist: secretstorage
Requires-Dist: shapely
Requires-Dist: smmap
Requires-Dist: tensorboard
Requires-Dist: tensorboard-data-server
Requires-Dist: tensorboard-plugin-wit
Requires-Dist: termcolor
Requires-Dist: terminaltables
Requires-Dist: thop
Requires-Dist: torch
Requires-Dist: torchaudio
Requires-Dist: torchvision
Requires-Dist: tqdm
Requires-Dist: twine
Requires-Dist: urllib3
Requires-Dist: watchdog
Requires-Dist: werkzeug
Requires-Dist: yolov5
Requires-Dist: zipp
Provides-Extra: dev
